needle/__init__.py
needle/__main__.py
needle/cli.py
needle/cmd/__app.py
needle/cmd/__init__.py
needle/cmd/haystack.py
needle/cmd/init.py
needle/cmd/render.py
needle/cmd/write.py
needle/config.py
needle/libs/__init__.py
needle/libs/adapters/__base.py
needle/libs/adapters/__init__.py
needle/libs/adapters/c.py
needle/libs/adapters/csharp.py
needle/libs/adapters/go.py
needle/libs/adapters/groovy.py
needle/libs/adapters/java.py
needle/libs/adapters/javascript.py
needle/libs/adapters/json.py
needle/libs/adapters/kotlin.py
needle/libs/adapters/markdown.py
needle/libs/adapters/php.py
needle/libs/adapters/powershell.py
needle/libs/adapters/python.py
needle/libs/adapters/r.py
needle/libs/adapters/rst.py
needle/libs/adapters/ruby.py
needle/libs/adapters/rust.py
needle/libs/adapters/scala.py
needle/libs/adapters/shell.py
needle/libs/adapters/swift.py
needle/libs/adapters/toml.py
needle/libs/adapters/xml.py
needle/libs/adapters/yaml.py
needle/libs/fs.py
needle/libs/parser.py
needle/libs/renderers/__base.py
needle/libs/renderers/__init__.py
needle/libs/renderers/handlebars.py
needle/libs/renderers/jinja.py
needle/libs/renderers/liquid.py
needle/libs/renderers/moustache.py
needle_cli-0.2.0.dist-info/METADATA
needle_cli-0.2.0.dist-info/WHEEL
needle_cli-0.2.0.dist-info/entry_points.txt
needle_cli-0.2.0.dist-info/RECORD
