Metadata-Version: 2.1
Name: needle-cli
Version: 0.2.0
Summary: 
License: MIT
Author: Jean-Michel Girard
Author-email: Jean.M.Girard@Outlook.com
Maintainer: Jean-Michel Girard
Maintainer-email: Jean.M.Girard@Outlook.com
Requires-Python: >=3.9,<4.0
Classifier: License :: OSI Approved :: MIT License
Classifier: Programming Language :: Python :: 3
Classifier: Programming Language :: Python :: 3.9
Classifier: Programming Language :: Python :: 3.10
Classifier: Programming Language :: Python :: 3.11
Requires-Dist: click (>=8.1.3,<9.0.0)
